tox_pip_extensions.py
tox_pip_extensions-1.6.0.dist-info/LICENSE
tox_pip_extensions-1.6.0.dist-info/METADATA
tox_pip_extensions-1.6.0.dist-info/WHEEL
tox_pip_extensions-1.6.0.dist-info/entry_points.txt
tox_pip_extensions-1.6.0.dist-info/top_level.txt
tox_pip_extensions-1.6.0.dist-info/RECORD
